{
  "session_id": "2",
  "parent_session_id": "1",
  "extracted_at": "2026-07-02T15:53:33.315774",
  "title": "竹棍点化",
  "characters": [
    {
      "name": "林霁",
      "外貌": "十六岁，清瘦，青布高马尾（耳侧碎发），左脸颊浅旧疤，虎口薄茧",
      "服装": "深青色交领短打（袖口收紧），灰色布腰带，麻编草鞋，浅灰色油衣半敞",
      "性格": "沉默执拗内在敏感且刚滋生出骄傲",
      "动机": "通过苦练获得出山寻父的资格（但被“恨意”和“远方”困住）",
      "弧光": "“急于向外求证” → “开始向内寻道”（被竹棍三击敲出种子）"
    },
    {
      "name": "师兄",
      "外貌": "约二十五岁，身形清癯，面庞清朗，眼神如古井，鬓角早生华发，虎口厚茧",
      "服装": "灰白色旧长衫（袖口宽大），腰间别竹笛，布靴沾干泥",
      "性格": "温和通透善于观察",
      "动机": "受人所托点拨林霁，让她从“用剑复仇/寻人”转向“以剑问道”",
      "弧光": "局外旁观者 → 薪火相传的点拨者"
    }
  ],
  "relationship_graph": "林霁 ↔ 点化她的师兄：从“困惑的求道者与被动的点拨者” → “种下问道之种的师徒关系”（未正式拜师，但本质是师承）",
  "world": {
    "地点": "师门后山岁考比武台",
    "时间": "黄昏（雨后初晴，约18:00-18:10）",
    "天气": "雨后，地面有浅水洼",
    "时代": "古代架空（武侠世界观）",
    "整体氛围": "雨后空寂的比武台，湿润宁静中有顿悟的微光"
  },
  "core_props": [
    "竹棍（承载点拨的三击）",
    "青锋剑（倒映林霁的视角转变）",
    "青石台面水洼倒影",
    "竹棍",
    "青锋剑",
    "师兄腰间竹笛"
  ],
  "tone": "静谧·悲伤·顿悟",
  "ending_state": "师兄离开后，林霁握剑看剑身倒影——不再看师父旁边空着的椅子，而是看向比武台外迷蒙的竹林，眼神从迷茫转为坚定。她知道寻找父亲的线索，不在“远方”，而藏在自己未来刺出的每一剑里。",
  "story_arc": [
    "S2: 岁考的喧哗已散，但林霁心中的快意还没凉透。她击败了二师兄，用巧劲破千钧——这本该是扬眉吐气的时刻。可师父旁边那把始终空着的椅子，像一根鱼刺卡在她喉咙里。\n\n**触发**：比武台空无一人，林霁独自在台上复盘每一个动作。她在想，自己赢了，然后呢？是用“师门最强新人”的名头继续练下去，还是用这身本事出山去找父亲？两个念头在心里角力，她的剑尖在青石板上无意识地划着。\n\n**发展**：一个她从未见过的男人不"
  ],
  "episode_id": 2
}